recipe/__init__.py
recipe/core.py
recipe/dynamic_extensions.py
recipe/exceptions.py
recipe/extensions.py
recipe/ingredients.py
recipe/shelf.py
recipe/oven/__init__.py
recipe/oven/base.py
recipe/oven/drivers/__init__.py
recipe/oven/drivers/standard_oven.py
recipe/schemas/__init__.py
recipe/schemas/builders.py
recipe/schemas/engine_support.py
recipe/schemas/expression_grammar.py
recipe/schemas/lark_grammar.py
recipe/schemas/parsed_constructors.py
recipe/schemas/parsed_schemas.py
recipe/schemas/transformers.py
recipe/schemas/utils.py
recipe/schemas/validators.py
recipe/utils/__init__.py
recipe/utils/anonymize.py
recipe/utils/datatype.py
recipe/utils/extensions.py
recipe/utils/formatting.py
recipe/utils/utils.py
recipe-0.37.2.dist-info/AUTHORS.rst
recipe-0.37.2.dist-info/LICENSE
recipe-0.37.2.dist-info/METADATA
recipe-0.37.2.dist-info/WHEEL
recipe-0.37.2.dist-info/entry_points.txt
recipe-0.37.2.dist-info/top_level.txt
recipe-0.37.2.dist-info/RECORD
