Metadata-Version: 2.1
Name: recipe
Version: 0.37.2
Summary: A construction kit for SQL
Home-page: https://github.com/juiceinc/recipe
Author: Chris Gemignani
Author-email: chris.gemignani@juiceanalytics.com
License: MIT
Classifier: Development Status :: 5 - Production/Stable
Classifier: Intended Audience :: Developers
Classifier: Natural Language :: English
Classifier: License :: OSI Approved :: MIT License
Classifier: Programming Language :: Python
Classifier: Programming Language :: Python :: 3.7
Classifier: Programming Language :: Python :: 3.8
Classifier: Programming Language :: Python :: 3.9
License-File: LICENSE
License-File: AUTHORS.rst
Requires-Dist: sqlalchemy (<2.0,>=1.4.0)
Requires-Dist: sqlparse
Requires-Dist: tablib
Requires-Dist: pyyaml
Requires-Dist: stevedore
Requires-Dist: sureberus
Requires-Dist: faker
Requires-Dist: dateparser (>=1.1.1)
Requires-Dist: attrs
Requires-Dist: lark
Requires-Dist: structlog
